{
  "subjectName": "dulsurgery",
  "lectures": [
    {
      "title": "1.Trauma.mp4",
      "streamingUrl": "https://stream6.nextpulse.workers.dev/watch/21808/1.Trauma.mp4?hash=AgADMB"
    },
    {
      "title": "2.Trauma and burn.mp4",
      "streamingUrl": "https://stream5.nextpulse.workers.dev/watch/21809/2.Trauma+and+burn.mp4?hash=AgADNB"
    },
    {
      "title": "3.liver.mp4",
      "streamingUrl": "https://stream5.nextpulse.workers.dev/watch/21810/3.liver.mp4?hash=AgADPB"
    },
    {
      "title": "4.Biliary system.mp4",
      "streamingUrl": "https://stream7.nextpulse.workers.dev/watch/21811/4.Biliary+system.mp4?hash=AgADPh"
    },
    {
      "title": "5.Bile duct injury and pancreas.mp4",
      "streamingUrl": "https://stream7.nextpulse.workers.dev/watch/21812/5.Bile+duct+injury+and+pancreas.mp4?hash=AgADQB"
    },
    {
      "title": "1. Esophagus",
      "streamingUrl": "https://stream2.nextpulse.workers.dev/watch/21813/1.+Esophagus?hash=AgADRh"
    },
    {
      "title": "2. Esophagus and GERD cancer.mp4",
      "streamingUrl": "https://stream2.nextpulse.workers.dev/watch/21814/2.+Esophagus+and+GERD+cancer.mp4?hash=AgADSx"
    },
    {
      "title": "3.stomach and peptic ulcer.mp4",
      "streamingUrl": "https://stream9.nextpulse.workers.dev/watch/21815/3.stomach+and+peptic+ulcer.mp4?hash=AgADUB"
    },
    {
      "title": "4.Gastric cancer and small intestine.mp4",
      "streamingUrl": "https://stream9.nextpulse.workers.dev/watch/21816/4.Gastric+cancer+and+small+intestine.mp4?hash=AgADWB"
    },
    {
      "title": "5.Small intestine and appendix.mp4",
      "streamingUrl": "https://stream8.nextpulse.workers.dev/watch/21817/5.Small+intestine+and+appendix.mp4?hash=AgADah"
    },
    {
      "title": "6.colorectal cancer.mp4",
      "streamingUrl": "https://stream8.nextpulse.workers.dev/watch/21818/6.colorectal+cancer.mp4?hash=AgADbx"
    },
    {
      "title": "7.Anal cancer,Hernia and Bariatric surgery.mp4",
      "streamingUrl": "https://stream3.nextpulse.workers.dev/watch/21819/7.Anal+cancer%2CHernia+and+Bariatric+surgery.mp4?hash=AgADdx"
    },
    {
      "title": "1. urology",
      "streamingUrl": "https://stream3.nextpulse.workers.dev/watch/21820/1.+urology?hash=AgADeh"
    },
    {
      "title": "2. urology",
      "streamingUrl": "https://stream4.nextpulse.workers.dev/watch/21821/2.+urology?hash=AgADfR"
    },
    {
      "title": "3. urology",
      "streamingUrl": "https://stream4.nextpulse.workers.dev/watch/21822/3.+urology?hash=AgADfx"
    },
    {
      "title": "3. Breast and skin cancer ♋♋ live in : 9.55 AM 11 April 2024",
      "streamingUrl": "https://stream6.nextpulse.workers.dev/watch/21823/3.+Breast+and+skin+cancer+%E2%99%8B%E2%99%8B+live+in+%3A+9.55+AM+11+April+2024?hash=AgADvx"
    },
    {
      "title": "1.1 Vascular disorders Live on: 05:00 pm 09 Apr, 2024",
      "streamingUrl": "https://stream6.nextpulse.workers.dev/watch/21824/1.1+Vascular+disorders+Live+on%3A+05%3A00+pm+09+Apr%2C+2024?hash=AgADLR"
    },
    {
      "title": "1.2 Vascular disorders Live on: 05:00 pm 09 Apr, 2024",
      "streamingUrl": "https://stream2.nextpulse.workers.dev/watch/21825/1.2+Vascular+disorders+Live+on%3A+05%3A00+pm+09+Apr%2C+2024?hash=AgADQh"
    },
    {
      "title": "2.1 Shock transplantation Live on: 05:00 pm 10 Apr, 2024",
      "streamingUrl": "https://stream2.nextpulse.workers.dev/watch/21826/2.1+Shock+transplantation+Live+on%3A+05%3A00+pm+10+Apr%2C+2024?hash=AgADRB"
    },
    {
      "title": "2.2 Shock ,transplantation Live on: 05:00 pm 10 Apr, 2024",
      "streamingUrl": "https://stream6.nextpulse.workers.dev/watch/21827/2.2+Shock+%2Ctransplantation+Live+on%3A+05%3A00+pm+10+Apr%2C+2024?hash=AgADTR"
    },
    {
      "title": "4.1 suture and wound healing.mp4",
      "streamingUrl": "https://stream6.nextpulse.workers.dev/watch/21828/4.1+suture+and+wound+healing.mp4?hash=AgAD4h"
    },
    {
      "title": "4.2 laparoscopic surgery,surgical infection.mp4",
      "streamingUrl": "https://stream4.nextpulse.workers.dev/watch/21829/4.2+laparoscopic+surgery%2Csurgical+infection.mp4?hash=AgADbx"
    },
    {
      "title": "1. Thyroid and parathyroid live - [ 5.00 PM ] - 15 April. 2024",
      "streamingUrl": "https://stream4.nextpulse.workers.dev/watch/21830/1.+Thyroid+and+parathyroid+live+-+%5B+5.00+PM+%5D+-+15+April.+2024?hash=AgADcR"
    },
    {
      "title": "2. Head and neck live on - 5 PM - 15 April 2024",
      "streamingUrl": "https://stream6.nextpulse.workers.dev/watch/21831/2.+Head+and+neck+live+on+-+5+PM+-+15+April+2024?hash=AgADeB"
    },
    {
      "title": "1.Head and Neck session 1 live on - 5.00 PM 15 April 2024",
      "streamingUrl": "https://stream6.nextpulse.workers.dev/watch/21832/1.Head+and+Neck+session+1+live+on+-+5.00+PM+15+April+2024?hash=AgADeh"
    },
    {
      "title": "1. Head and Neck session 2 live on - 5 PM 15 April 2024",
      "streamingUrl": "https://stream10.nextpulse.workers.dev/watch/21833/1.+Head+and+Neck+session+2+live+on+-+5+PM+15+April+2024?hash=AgADex"
    },
    {
      "title": "Surgery Urology Dr Sujoy.mp4",
      "streamingUrl": "https://stream10.nextpulse.workers.dev/watch/21834/Surgery+Urology+Dr+Sujoy.mp4?hash=AgADfB"
    },
    {
      "title": "1. Esophagus 1.mp4",
      "streamingUrl": "https://stream8.nextpulse.workers.dev/watch/21835/1.+Esophagus+1.mp4?hash=AgADmh"
    },
    {
      "title": "2. Esophagus 2.mp4",
      "streamingUrl": "https://stream8.nextpulse.workers.dev/watch/21836/2.+Esophagus+2.mp4?hash=AgADnh"
    },
    {
      "title": "3. Gastric ulcer.mp4",
      "streamingUrl": "https://stream2.nextpulse.workers.dev/watch/21837/3.+Gastric+ulcer.mp4?hash=AgADpR"
    },
    {
      "title": "4. Gastric cancer and SI.mp4",
      "streamingUrl": "https://stream2.nextpulse.workers.dev/watch/21838/4.+Gastric+cancer+and+SI.mp4?hash=AgADsR"
    },
    {
      "title": "5. Appendix and hernia.mp4",
      "streamingUrl": "https://stream8.nextpulse.workers.dev/watch/21839/5.+Appendix+and+hernia.mp4?hash=AgADuB"
    },
    {
      "title": "6. Surgery GIT.mp4",
      "streamingUrl": "https://stream8.nextpulse.workers.dev/watch/21840/6.+Surgery+GIT.mp4?hash=AgADxh"
    },
    {
      "title": "1. Surgery- HBP - Trauma and burns.mp4",
      "streamingUrl": "https://stream3.nextpulse.workers.dev/watch/21841/1.+Surgery-+HBP+-+Trauma+and+burns.mp4?hash=AgADzB"
    },
    {
      "title": "2. Surgery- HBP - Trauma and burns.mp4",
      "streamingUrl": "https://stream3.nextpulse.workers.dev/watch/21842/2.+Surgery-+HBP+-+Trauma+and+burns.mp4?hash=AgADzx"
    },
    {
      "title": "3. Surgery- HBP - Trauma and burns.mp4",
      "streamingUrl": "https://stream9.nextpulse.workers.dev/watch/21843/3.+Surgery-+HBP+-+Trauma+and+burns.mp4?hash=AgAD0R"
    },
    {
      "title": "4. Surgery- HBP - Trauma and burns.mp4.mp4",
      "streamingUrl": "https://stream9.nextpulse.workers.dev/watch/21844/4.+Surgery-+HBP+-+Trauma+and+burns.mp4.mp4?hash=AgAD0x"
    },
    {
      "title": "5. Surgery- HBP - Trauma and burns.mp4",
      "streamingUrl": "https://stream8.nextpulse.workers.dev/watch/21845/5.+Surgery-+HBP+-+Trauma+and+burns.mp4?hash=AgAD1x"
    },
    {
      "title": "1. Surgery urology ultimate.mp4",
      "streamingUrl": "https://stream8.nextpulse.workers.dev/watch/21846/1.+Surgery+urology+ultimate.mp4?hash=AgAD2B"
    },
    {
      "title": "2. Urology.mp4",
      "streamingUrl": "https://stream10.nextpulse.workers.dev/watch/21847/2.+Urology.mp4?hash=AgAD3R"
    },
    {
      "title": "3. Urology.mp4",
      "streamingUrl": "https://stream10.nextpulse.workers.dev/watch/21848/3.+Urology.mp4?hash=AgAD9x"
    },
    {
      "title": "3. Urology session 1.mp4",
      "streamingUrl": "https://stream9.nextpulse.workers.dev/watch/21849/3.+Urology+session+1.mp4?hash=AgAD_h"
    },
    {
      "title": "1 1 Thyroid ( Head & Neck).mp4",
      "streamingUrl": "https://stream9.nextpulse.workers.dev/watch/21850/1+1+Thyroid+%28+Head+%26+Neck%29.mp4?hash=AgADjR"
    },
    {
      "title": "1.2 Thyroid ( Head & Neck).mp4",
      "streamingUrl": "https://stream10.nextpulse.workers.dev/watch/21851/1.2+Thyroid+%28+Head+%26+Neck%29.mp4?hash=AgADbS"
    },
    {
      "title": "2.1 Thyroid cancer & Malignancy (Head & Neck).mp4",
      "streamingUrl": "https://stream10.nextpulse.workers.dev/watch/21852/2.1+Thyroid+cancer+%26+Malignancy+%28Head+%26+Neck%29.mp4?hash=AgADrh"
    },
    {
      "title": "2.2 Adrenal, MEN Syndrome, Graft flaps- (Head & Neck).mp4",
      "streamingUrl": "https://stream9.nextpulse.workers.dev/watch/21853/2.2+Adrenal%2C+MEN+Syndrome%2C+Graft+flaps-+%28Head+%26+Neck%29.mp4?hash=AgADzS"
    },
    {
      "title": "3.1 Venous, Arterial disorders (General Surgery).mp4",
      "streamingUrl": "https://stream9.nextpulse.workers.dev/watch/21854/3.1+Venous%2C+Arterial+disorders+%28General+Surgery%29.mp4?hash=AgADoh"
    },
    {
      "title": "3.2 Arterial disorders (General Surgery).mp4",
      "streamingUrl": "https://stream8.nextpulse.workers.dev/watch/21855/3.2+Arterial+disorders+%28General+Surgery%29.mp4?hash=AgADex"
    },
    {
      "title": "4.1 Arterial, shock ,Sutures (General Surgery).mp4",
      "streamingUrl": "https://stream8.nextpulse.workers.dev/watch/21856/4.1+Arterial%2C+shock+%2CSutures+%28General+Surgery%29.mp4?hash=AgADGR"
    },
    {
      "title": "4.2 Sutures (General Surgery) .mp4",
      "streamingUrl": "https://stream5.nextpulse.workers.dev/watch/21857/4.2+Sutures+%28General+Surgery%29+.mp4?hash=AgADOh"
    },
    {
      "title": "5.1 Breast Anatomy, Breast cancer 1 (General Surgery).mp4",
      "streamingUrl": "https://stream5.nextpulse.workers.dev/watch/21858/5.1+Breast+Anatomy%2C+Breast+cancer+1+%28General+Surgery%29.mp4?hash=AgADIB"
    },
    {
      "title": "5.2 Investigation Breast cancer (General Surgery).mp4",
      "streamingUrl": "https://stream6.nextpulse.workers.dev/watch/21859/5.2+Investigation+Breast+cancer+%28General+Surgery%29.mp4?hash=AgADHR"
    },
    {
      "title": "6. Investigation Breast Cancer part 2, Benign Breast Disorders & Basics of laproscopy, Nutrition in Surgical patients(General Surgery).mp4",
      "streamingUrl": "https://stream6.nextpulse.workers.dev/watch/21860/6.+Investigation+Breast+Cancer+part+2%2C+Benign+Breast+Disorders+%26+Basics+of+laproscopy%2C+Nutrition+in+Surgical+patients%28General+Surgery%29.mp4?hash=AgADYi"
    },
    {
      "title": "7.1 Transplant .mp4",
      "streamingUrl": "https://stream3.nextpulse.workers.dev/watch/21861/7.1+Transplant+.mp4?hash=AgADUx"
    },
    {
      "title": "7.2 Surgical infection .mp4",
      "streamingUrl": "https://stream3.nextpulse.workers.dev/watch/21862/7.2+Surgical+infection+.mp4?hash=AgADRC"
    },
    {
      "title": "8. Cleft Disorders,Oral cavity cancer & Salivary Gland.mp4",
      "streamingUrl": "https://stream1.nextpulse.workers.dev/watch/21863/8.+Cleft+Disorders%2COral+cavity+cancer+%26+Salivary+Gland.mp4?hash=AgADLz"
    },
    {
      "title": "9.1 Esophagus 1.mp4",
      "streamingUrl": "https://stream1.nextpulse.workers.dev/watch/21864/9.1+Esophagus+1.mp4?hash=AgADrj"
    },
    {
      "title": "9.2 Esophagus 1.mp4",
      "streamingUrl": "https://stream2.nextpulse.workers.dev/watch/21865/9.2+Esophagus+1.mp4?hash=AgADLz"
    },
    {
      "title": "10.1 Esophagus 2.mp4",
      "streamingUrl": "https://stream2.nextpulse.workers.dev/watch/21866/10.1+Esophagus+2.mp4?hash=AgADrB"
    },
    {
      "title": "10.2 Stomach 1.mp4",
      "streamingUrl": "https://stream9.nextpulse.workers.dev/watch/21867/10.2+Stomach+1.mp4?hash=AgADtE"
    },
    {
      "title": "11.1 Stomach 2 (GIT).mp4",
      "streamingUrl": "https://stream9.nextpulse.workers.dev/watch/21868/11.1+Stomach+2+%28GIT%29.mp4?hash=AgADrR"
    },
    {
      "title": "11.2 Stomach 3 (GIT).mp4",
      "streamingUrl": "https://stream7.nextpulse.workers.dev/watch/21869/11.2+Stomach+3+%28GIT%29.mp4?hash=AgADw0"
    },
    {
      "title": "12.1 Stomach (GIT).mp4",
      "streamingUrl": "https://stream7.nextpulse.workers.dev/watch/21870/12.1+Stomach+%28GIT%29.mp4?hash=AgADdk"
    },
    {
      "title": "12.2 Intestine - I (GIT).mp4",
      "streamingUrl": "https://stream10.nextpulse.workers.dev/watch/21871/12.2+Intestine+-+I+%28GIT%29.mp4?hash=AgAD5U"
    },
    {
      "title": "13.1 Appendix (GIT).mp4",
      "streamingUrl": "https://stream10.nextpulse.workers.dev/watch/21872/13.1+Appendix+%28GIT%29.mp4?hash=AgADX0"
    },
    {
      "title": "13.2 Colon Minor (GIT).mp4",
      "streamingUrl": "https://stream4.nextpulse.workers.dev/watch/21873/13.2+Colon+Minor+%28GIT%29.mp4?hash=AgADt0"
    },
    {
      "title": "13.3 Colorectal Cancer 1 (GIT).mp4",
      "streamingUrl": "https://stream4.nextpulse.workers.dev/watch/21874/13.3+Colorectal+Cancer+1+%28GIT%29.mp4?hash=AgADvE"
    },
    {
      "title": "14.1 Colorectal Cancer 2 (GIT).mp4",
      "streamingUrl": "https://stream8.nextpulse.workers.dev/watch/21875/14.1+Colorectal+Cancer+2+%28GIT%29.mp4?hash=AgAD3E"
    },
    {
      "title": "14.2 CRC 3 (Rectal Cancer) and anal canal (GIT).mp4",
      "streamingUrl": "https://stream8.nextpulse.workers.dev/watch/21876/14.2+CRC+3+%28Rectal+Cancer%29+and+anal+canal+%28GIT%29.mp4?hash=AgADxk"
    },
    {
      "title": "15.1 Hernia 1(GIT).mp4",
      "streamingUrl": "https://stream6.nextpulse.workers.dev/watch/21877/15.1+Hernia+1%28GIT%29.mp4?hash=AgADwR"
    },
    {
      "title": "15.2 Hernia 2 (GIT).mp4",
      "streamingUrl": "https://stream6.nextpulse.workers.dev/watch/21878/15.2+Hernia+2+%28GIT%29.mp4?hash=AgADlR"
    },
    {
      "title": "16.1 Bariatric surgery and minor Topics.mp4",
      "streamingUrl": "https://stream1.nextpulse.workers.dev/watch/21879/16.1+Bariatric+surgery+and+minor+Topics.mp4?hash=AgAD0B"
    },
    {
      "title": "1.1 Trauma- General, Scores, Thoracic Trauma.mp4",
      "streamingUrl": "https://stream1.nextpulse.workers.dev/watch/21880/1.1+Trauma-+General%2C+Scores%2C+Thoracic+Trauma.mp4?hash=AgAD0C"
    },
    {
      "title": "1.2 Thoracic, Abdominal Trauma.mp4",
      "streamingUrl": "https://stream3.nextpulse.workers.dev/watch/21881/1.2+Thoracic%2C+Abdominal+Trauma.mp4?hash=AgADhC"
    },
    {
      "title": "2.1 Trauma, DCS, ACS, Head & neck Trauma.mp4",
      "streamingUrl": "https://stream3.nextpulse.workers.dev/watch/21882/2.1+Trauma%2C+DCS%2C+ACS%2C+Head+%26+neck+Trauma.mp4?hash=AgAD9C"
    },
    {
      "title": "2.2 Burn, Liver anatomy.mp4",
      "streamingUrl": "https://stream7.nextpulse.workers.dev/watch/21883/2.2+Burn%2C+Liver+anatomy.mp4?hash=AgAD8S"
    },
    {
      "title": "3.1 Liver- Infection, Portal Hypertension, Tumours.mp4",
      "streamingUrl": "https://stream7.nextpulse.workers.dev/watch/21884/3.1+Liver-+Infection%2C+Portal+Hypertension%2C+Tumours.mp4?hash=AgADgj"
    },
    {
      "title": "3.2 Biliary system- Anatomy & congenital disorders.mp4",
      "streamingUrl": "https://stream10.nextpulse.workers.dev/watch/21885/3.2+Biliary+system-+Anatomy+%26+congenital+disorders.mp4?hash=AgADpB"
    },
    {
      "title": "4.1 Gallbladder disorders.mp4",
      "streamingUrl": "https://stream10.nextpulse.workers.dev/watch/21886/4.1+Gallbladder+disorders.mp4?hash=AgADHy"
    },
    {
      "title": "4.2 Biliary Tract Disorders.mp4",
      "streamingUrl": "https://stream7.nextpulse.workers.dev/watch/21887/4.2+Biliary+Tract+Disorders.mp4?hash=AgADVi"
    },
    {
      "title": "<b>5.1 Pancreas.mp4</b>",
      "streamingUrl": "https://stream7.nextpulse.workers.dev/watch/21888/%3Cb%3E5.1+Pancreas.mp4%3C%2Fb%3E?hash=AgADUi"
    },
    {
      "title": "<b>5.2 Pancreatic Malignancy.mp4</b>",
      "streamingUrl": "https://stream1.nextpulse.workers.dev/watch/21889/%3Cb%3E5.2+Pancreatic+Malignancy.mp4%3C%2Fb%3E?hash=AgADxh"
    },
    {
      "title": "<b>1. Surgery (Urology) Ultimate 2025.mp4</b>",
      "streamingUrl": "https://stream1.nextpulse.workers.dev/watch/21890/%3Cb%3E1.+Surgery+%28Urology%29+Ultimate+2025.mp4%3C%2Fb%3E?hash=AgADty"
    },
    {
      "title": "<b>2. Surgery (Urology) Ultimate 2025.mp4</b>",
      "streamingUrl": "https://stream6.nextpulse.workers.dev/watch/21891/%3Cb%3E2.+Surgery+%28Urology%29+Ultimate+2025.mp4%3C%2Fb%3E?hash=AgADIC"
    }
  ]
}